cveutils/__init__.py
cveutils/cveutils.py
cveutils-0.6.dist-info/LICENSE
cveutils-0.6.dist-info/METADATA
cveutils-0.6.dist-info/WHEEL
cveutils-0.6.dist-info/top_level.txt
cveutils-0.6.dist-info/RECORD
